setup.cfg
setup.py
spielbash/__init__.py
spielbash.egg-info/PKG-INFO
spielbash.egg-info/SOURCES.txt
spielbash.egg-info/dependency_links.txt
spielbash.egg-info/entry_points.txt
spielbash.egg-info/top_level.txt
spielbash/tests/__init__.py