Metadata-Version: 1.1
Name: spielbash
Version: 0.1.4
Summary: an automator for asciinema bash movies
Home-page: http://softwarefactory-project.io/r/gitweb?p=spielbash.git
Author: Software Factory team.
Author-email: softwarefactory@redhat.com
License: Apache v2.0
Platform: UNKNOWN
Classifier: Environment :: Console
Classifier: Intended Audience :: Developers
Classifier: Intended Audience :: Information Technology
Classifier: License :: OSI Approved :: Apache Software License
Classifier: Operating System :: POSIX :: Linux
Classifier: Programming Language :: Python :: 2.7
Classifier: Topic :: System :: Distributed Computing
